{
    "Version": "2012-10-17",
    "Statement": [
        {
            "Effect": "Allow",
            "Principal": {
                "AWS": "arn:aws:iam::111122223333:role/jenkins-terraform-role"
            },
            "Action": "s3:ListBucket",
            "Resource": "arn:aws:s3:::jenkins-terraform-backend-store1"
        },
        {
            "Effect": "Allow",
            "Principal": {
                "AWS": "arn:aws:iam::111122223333:role/jenkins-terraform-role"
            },
            "Action": [
                "s3:GetObject",
                "s3:PutObject",
                "s3:DeleteObject"
            ],
            "Resource": "arn:aws:s3:::jenkins-terraform-backend-store1/stage1/terraform.tfstate"
        }
    ]
}
